klv_system_monitor/__init__.py
klv_system_monitor/klv_system_monitor.py
klv_system_monitor/list_disks.py
klv_system_monitor/data_acquisition/__init__.py
klv_system_monitor/data_acquisition/cpu.py
klv_system_monitor/data_acquisition/disks.py
klv_system_monitor/data_acquisition/memory.py
klv_system_monitor/data_acquisition/network.py
klv_system_monitor/data_acquisition/processes.py
klv_system_monitor/miscellaneous/images/Karel.jpeg
klv_system_monitor/miscellaneous/images/icon.png
klv_system_monitor-0.1.5.dist-info/licenses/LICENSE
klv_system_monitor-0.1.5.dist-info/METADATA
klv_system_monitor-0.1.5.dist-info/WHEEL
klv_system_monitor-0.1.5.dist-info/entry_points.txt
klv_system_monitor-0.1.5.dist-info/top_level.txt
klv_system_monitor-0.1.5.dist-info/RECORD
