Metadata-Version: 2.4
Name: klv-system-monitor
Version: 0.1.5
Summary: Cross-platform-ish system monitor (tested on Linux & Windows). Clean PyQt UI for CPU, memory, network and filesystems.
Author-email: Karel López Vilaret <karel.mauricio.lopez.vilaret@uni-oldenburg.de>
License: MIT License
Project-URL: Homepage, https://github.com/karellopez/KLV-System-Monitor
Project-URL: Repository, https://github.com/karellopez/KLV-System-Monitor
Project-URL: Issues, https://github.com/karellopez/KLV-System-Monitor/issues
Project-URL: Changelog, https://github.com/karellopez/KLV-System-Monitor/releases
Project-URL: Author (LinkedIn), https://www.linkedin.com/in/karel-l%C3%B3pez-vilaret/
Keywords: system monitor,monitoring,psutil,PyQt5,pyqtgraph,CPU,memory,network,filesystem,Linux,Windows
Classifier: Development Status :: 3 - Alpha
Classifier: Environment :: X11 Applications :: Qt
Classifier: Environment :: Win32 (MS Windows)
Classifier: Intended Audience :: End Users/Desktop
Classifier: Intended Audience :: Developers
Classifier: License :: OSI Approved
Classifier: Programming Language :: Python :: 3
Classifier: Programming Language :: Python :: 3 :: Only
Classifier: Programming Language :: Python :: 3.9
Classifier: Programming Language :: Python :: 3.10
Classifier: Programming Language :: Python :: 3.11
Classifier: Programming Language :: Python :: 3.12
Classifier: Topic :: Desktop Environment
Classifier: Topic :: System :: Monitoring
Classifier: Operating System :: POSIX :: Linux
Classifier: Operating System :: Microsoft :: Windows
Requires-Python: >=3.9
License-File: LICENSE
Requires-Dist: PyQt5==5.15.11
Requires-Dist: pyqtgraph==0.13.7
Requires-Dist: psutil==7.0.0
Provides-Extra: gpu-nvidia
Requires-Dist: nvidia-ml-py3>=7.352.0; extra == "gpu-nvidia"
Provides-Extra: dev
Requires-Dist: pytest; extra == "dev"
Requires-Dist: mypy; extra == "dev"
Requires-Dist: ruff; extra == "dev"
Requires-Dist: black; extra == "dev"
Requires-Dist: build; extra == "dev"
Requires-Dist: twine; extra == "dev"
Dynamic: license-file
